pylib/__init__.py
pylib/String/Random.py
pylib/String/__init__.py
pylib/db/__init__.py
pylib/db/url.py
pylib/db/mysql/__init__.py
pylib/hash/__init__.py
pylib/net/__init__.py
pylib/net/http/__init__.py
pylib/net/http/get.py
pylib/objects/Iter.py
pylib/objects/__init__.py
pylib/sys/__init__.py
pylib/sys/multithread.py
pylib/time/__init__.py
pylib/time/timerange.py
pylib-1.0.10.dist-info/DESCRIPTION.rst
pylib-1.0.10.dist-info/METADATA
pylib-1.0.10.dist-info/RECORD
pylib-1.0.10.dist-info/WHEEL
pylib-1.0.10.dist-info/metadata.json
pylib-1.0.10.dist-info/top_level.txt
